plush/__init__.py
plush/console.py
plush/oauth_flow.py
plush/repo_keys.py
plush/fabric_commands/__init__.py
plush/fabric_commands/git.py
plush/fabric_commands/permissions.py
plush/fabric_commands/ssh_key.py
plush/patchwork/__init__.py
plush/patchwork/files.py
plush/patchwork/util.py
plush_fabric-1.1.2.dist-info/licenses/LICENSE.TXT
plush_fabric-1.1.2.dist-info/METADATA
plush_fabric-1.1.2.dist-info/WHEEL
plush_fabric-1.1.2.dist-info/entry_points.txt
plush_fabric-1.1.2.dist-info/top_level.txt
plush_fabric-1.1.2.dist-info/RECORD
