Metadata-Version: 2.4
Name: plush-fabric
Version: 1.1.2
Summary: Helper library for Fabric to simplify creating and managing GitHub deploy keys when deploying GitHub-hosted repositories
Author-email: Kevin Barnes <kbarnes3@gmail.com>
Project-URL: Homepage, https://github.com/kbarnes3/Plush
Project-URL: Issues, https://github.com/kbarnes3/Plush/issues
Keywords: Fabric,GitHub,deployment
Classifier: Programming Language :: Python :: 3
Classifier: Programming Language :: Python :: 3.12
Classifier: License :: OSI Approved :: MIT License
Classifier: Operating System :: OS Independent
Classifier: Development Status :: 4 - Beta
Classifier: Intended Audience :: Developers
Classifier: Topic :: Software Development
Requires-Python: >=3.12
License-File: LICENSE.TXT
Requires-Dist: oauth2client>=4.1.3
Requires-Dist: PyGithub>=2.8.1
Requires-Dist: keyring>=25.6.0
Requires-Dist: fabric>=3.2.2
Requires-Dist: colorama>=0.4.6
Provides-Extra: test
Requires-Dist: pylint; extra == "test"
Provides-Extra: publish
Requires-Dist: build; extra == "publish"
Requires-Dist: twine; extra == "publish"
Dynamic: license-file
